lunni_cli/__init__.py
lunni_cli/__main__.py
lunni_cli/app.py
lunni_cli/commands/__init__.py
lunni_cli/commands/create.py
lunni_cli/commands/docker.py
lunni_cli/commands/version.py
lunni_cli-0.1.1.dist-info/LICENSE
lunni_cli-0.1.1.dist-info/METADATA
lunni_cli-0.1.1.dist-info/WHEEL
lunni_cli-0.1.1.dist-info/entry_points.txt
lunni_cli-0.1.1.dist-info/RECORD
