Metadata-Version: 2.1
Name: lunni-cli
Version: 0.1.1
Summary: Lunni's CLI companion
Home-page: https://lunni.dev/
License: Apache-2.0
Keywords: docker,swarm,cli,deploy
Author: Alexander Pushkov
Author-email: ale@aedge.dev
Requires-Python: >=3.9,<4.0
Classifier: Development Status :: 4 - Beta
Classifier: Environment :: Console
Classifier: License :: OSI Approved :: Apache Software License
Classifier: Natural Language :: English
Classifier: Programming Language :: Python :: 3
Classifier: Programming Language :: Python :: 3.9
Classifier: Programming Language :: Python :: 3.10
Classifier: Programming Language :: Python :: 3.11
Classifier: Topic :: Software Development
Classifier: Topic :: System :: Software Distribution
Requires-Dist: cookiecutter (>=2.1.1,<3.0.0)
Requires-Dist: typer (>=0.7.0,<0.8.0)
Project-URL: Bug Tracker, https://gitlab.com/lunni/lunni-cli/-/issues
Project-URL: Documentation, https://lunni.dev/docs/cli/
Project-URL: Repository, https://gitlab.com/lunni/lunni-cli
